{"id":219,"inkURL":"http://sharkeylab.org/sharkeylab/Misc/datasets/Proctotrupoidea.ink","title":"Proctotrupoidea","imagePath":"http://www.uky.edu/~mjshar0/datasets/Proctotrupoidea","characters":[{"type":"UM","states":["yes, greater than 2 cm","no, less than 2 cm"],"id":1,"name":"Is the body greater than 2 centimeters in length?","data":[1,2,2,2,2,2,2,2,2,2,2]},{"type":"UM","states":["yes","no, not forked or absent"],"id":2,"name":"Is forewing vein Rs forked?","images":[{"f":"RSFORKED.jpg","n":""}],"data":[1,2,2,2,2,2,2,2,2,2,0]},{"type":"UM","states":["yes","no, pointed inward or rarely absent"],"id":3,"name":"Are the teeth of the mandible pointed outward (exodont)?","images":[{"f":"EXODONT.jpg","n":""}],"data":[2,1,2,2,2,2,2,2,2,2,2]},{"type":"UM","states":["yes","no"],"id":4,"name":"Is the ovipositor directed anteriorly, between the legs, and housed in a ventral groove on the metasoma?","images":[{"f":"OVIPOSITORFORWARD.jpg","n":""}],"data":[2,1,2,2,2,2,2,2,2,2,2]},{"type":"UM","states":["yes (termed the \\ul{}syntergum\\ulnone{}, this is actually the fusion of tergites 1-3)","no"],"id":5,"name":"Is apparent metasomal tergum 1 the largest?","images":[{"f":"SYNTERGUM.jpg","n":""}],"data":[0,1,2,2,2,2,2,2,2,2,2]},{"type":"UM","states":["yes","no, tergum 2 is almost equal to tergum 3"],"id":6,"name":"Is tergum 2 (true or apparent) several times longer than tergum 3 (true or apparent)?","images":[{"f":"TERGUMTWO.jpg","n":""}],"data":[2,0,2,2,1,1,1,1,1,2,2]},{"type":"UM","states":["yes","no, the metasoma is short (not tail-like)"],"id":7,"name":"Is the metasoma long and slender, almost tail-like in appearance?","images":[{"f":"TAILLIKE.jpg","n":""}],"data":[[1,2],2,[1,2],2,2,2,[1,2],2,0,2,2]},{"type":"UM","states":["metasomal segment 1 is at least three times longer than wide","metasoma segment 1 is at most twice as long as wide"],"id":8,"name":"Is metasomal segment 1 (true or apparent) at least 3 times longer than wide?","images":[{"f":"SEGMENTONE.jpg","n":""}],"data":[1,1,1,2,[1,2],1,2,1,[1,2],1,2]},{"type":"UM","states":["yes","no, the tarsal claw is simple"],"id":9,"name":"Is there a rectangular lobe at the base of the tarsal claws?","data":[2,1,2,1,2,2,[1,2],0,0,0,2]},{"type":"UM","states":["Australian","Ethiopian","Nearctic","Neotropical","Oriental","Palearctic"],"id":10,"name":"In which biogeographic realm was the specimen collected?","images":[{"f":"Map.jpg","n":""}],"data":[[3,4],[3,5,6],[1,4],1,[1,2,3,4,5,6],1,[1,2,3,4,5,6],[3,5,6],[1,2,3,4,5,6],[3,6],1]},{"type":"UM","states":["yes","no"],"id":11,"name":"Do the antenna appear to sit on an antennal shelf when viewed laterally?","images":[{"f":"ANTENNALSHELF.jpg","n":""}],"data":[1,2,2,2,[1,2],2,2,2,2,2,1]},{"type":"UM","states":["the scape is at least 2.5 times as long as wide","the scape is at most 2.2 times as long as wide"],"id":12,"name":"Is the scape at least 2.5 times longer than wide?","images":[{"f":"SCAPE.jpg","n":""}],"data":[2,0,[1,2],2,1,2,2,2,2,2,1]},{"type":"UM","states":["yes","no"],"id":13,"name":"Are tubular veins present on the forewing?","images":[{"f":"TUBULARVEING.jpg","n":""}],"data":[1,1,1,1,[1,2],1,1,1,1,1,1]},{"type":"UM","states":["yes, the stigma is elongate or thick","no, at most it is linear or spot-like"],"id":14,"name":"Is the stigma of the forewing clearly indicated?","images":[{"f":"STIGMA.jpg","n":""}],"data":[1,1,[1,2],1,2,1,1,1,1,1,2]},{"type":"IN","min":2,"max":13,"unit":"If a ring-like first flagellomere (\\ul{}anellus\\ulnone{}) is present, do not include it in the total number of flagellomeres.","id":15,"name":"How many flagellomeres does the antenna have (not including the anellus)?","data":[12,11,12,12,[2,3,4,5,6,7,8,9,10,11,12,13],11,11,12,11,12,[12,13]]},{"type":"UM","states":["yes","no"],"id":16,"name":"Does the forewing have a first discal cell?","images":[{"f":"FIRSTDISCALPRESENT.jpg","n":""}],"data":[2,1,2,2,2,2,2,1,1,1,2]},{"type":"UM","states":["the first discal cell has 4 or more sides","the first discal cell has 3 sides, and is almost triangular in appearance"],"id":17,"name":"What is the shape of the first discal cell of the forewing?","images":[{"f":"FIRSTDISCAL.jpg","n":""}],"data":[0,1,0,0,0,0,0,1,2,1,0]},{"type":"UM","states":["yes","no, it is nebulous or absent"],"id":18,"name":"Is vein (Rs+M)a of the forewing tubular?","images":[{"f":"RSVEIN.jpg","n":""}],"data":[0,1,1,1,[1,2],2,2,1,1,1,1]},{"type":"UM","states":["yes, as long or longer","no, shorter"],"id":19,"name":"Is metasomal segment one (true or apparent) as long as the rest of metasoma?","images":[{"f":"SYNTERGUM.jpg","n":""}],"data":[[1,2],1,[1,2],2,2,1,2,[1,2],2,2,2]},{"type":"UM","states":["yes, the hind tibia is swollen toward the apex, appearing club-shaped","no"],"id":20,"name":"Does the hind tibia appear swollen and club-shaped?","images":[{"f":"SWOLLENHINDTIBIA.jpg","n":""}],"data":[[1,2],2,2,2,[1,2],1,2,2,2,2,2]},{"type":"UM","states":["yes","no"],"id":21,"name":"Do the inner margins of the eyes strongly converge ventrally?","images":[{"f":"EYESCONVERGE.jpg","n":""}],"data":[2,2,2,2,[1,2],1,2,2,2,1,2]},{"type":"UM","states":["separated by more than its own diameter","separated by its own diameter or less"],"id":22,"name":"How far is the lateral ocellus separated from the eye?","images":[{"f":"LATERALOCELLUS.jpg","n":""}],"data":[1,1,1,1,1,2,1,1,1,1,1]},{"type":"UM","states":["yes","no"],"id":23,"name":"Is the basal flagellomere ring-like (not longer than wide)?","images":[{"f":"RINGLIKE.jpg","n":""}],"data":[2,2,2,2,2,2,2,[1,2],1,[1,2],2]},{"type":"UM","states":["yes, the metasoma is higher than wide in lateral view","no, metasoma is slightly wider than high in lateral view"],"id":24,"name":"Is the metasoma, beyond the first segment, strongly laterally compressed?","images":[{"f":"METASOMALATERALLYCOMPRESSED.jpg","n":""}],"data":[2,2,[1,2],2,2,2,2,1,2,2,2]},{"type":"UM","states":["yes","no"],"id":25,"name":"Is vein 1Rs present on the forewing?","images":[{"f":"RS1.jpg","n":""}],"data":[0,0,0,0,0,0,0,1,2,0,0]}],"taxa":[{"id":1,"name":"Pelecinidae","images":[{"f":"pelicinidae.jpg","n":""},{"f":"MALEPELECINIDAE.jpg","n":""}]},{"id":2,"name":"Vanhorniidae","images":[{"f":"vanhornia2habitusMontage.jpg","n":""}]},{"id":3,"name":"Monomachidae","images":[{"f":"Monomachidae_male.jpg","n":""},{"f":"Monomachidae.jpg","n":""}]},{"id":4,"name":"Austroniidae","images":[{"f":"Austroniidae.jpg","n":""}]},{"id":5,"name":"Diapriidae","images":[{"f":"diapriidae2.jpg","n":""},{"f":"diapriidae.jpg","n":""},{"f":"lateral_habitus.jpg","n":""},{"f":"Belytinae_dorsal.jpg","n":""},{"f":"Platymischus_dilatatus.jpg","n":""}]},{"id":6,"name":"Peradeniidae","images":[{"f":"Peradeniidae.jpg","n":""}]},{"id":7,"name":"Proctotrupidae","images":[{"f":"proctotrupidaelateralhabitus.jpg","n":""}]},{"id":8,"name":"Roproniidae","images":[{"f":"roproniidaehabitus.jpg","n":""}]},{"id":9,"name":"Heloridae","images":[{"f":"heloridaehabitus.jpg","n":""}]},{"id":10,"name":"Proctorenyxidae","images":[{"f":"proctorenyxidae.jpg","n":""}]},{"id":11,"name":"Maamingidae","images":[{"f":"Maamingidae_male.jpg","n":""},{"f":"Maamingidae.jpg","n":""}]}],"dataDir":"sharkeylab_org_sharkeylab_Misc_datasets_Proctotrupoidea"}