{"id":159,"inkURL":"http://flora.huh.harvard.edu/china/delta/Garcinia.ink","title":"Garcinia of China 08:44 01-NOV-07","imagePath":"","characters":[{"type":"UM","states":["shrub","tree"],"id":1,"name":"plant: habit","data":[2,2,[1,2],2,2,2,2,2,2,2,2,2,[1,2],2,1,2,2,2,2,2]},{"type":"RN","unit":"m tall","id":2,"name":"plant: height","data":["8-10","1-3","3-15","10-20","20-20","6-15","12-20","8-8","3-25","6-6","10-15","8-12","5-15","4-4","1-3","7-7","15-20","5-15","3-6","10-15"]},{"type":"RN","unit":"cm","id":3,"name":"tree: diam.","data":["15-45",0,"20-40","15-30",0,0,0,0,0,0,"20-30","15-20","15-30",0,0,"15-15",0,"15-15",0,0]},{"type":"UM","states":["black","brown","gray","purple","white spotted"],"id":4,"name":"bark: color","data":[[2,3],0,3,0,0,0,0,0,[1,3,5],0,[2,3],2,3,4,0,2,0,0,0,0]},{"type":"UM","states":["brown","gray","green","purple","red","yellow"],"id":5,"name":"twig: color","data":[0,0,2,[1,2],0,3,0,3,4,[1,5],[1,2],1,0,[4,5],0,0,0,3,0,[1,6]]},{"type":"UM","states":["angled","terete"],"id":6,"name":"twig: cross-section","data":[1,1,1,0,0,2,1,0,0,1,0,0,0,2,0,0,0,1,0,1]},{"type":"RN","unit":"mm","id":7,"name":"leaf: petiole: length","data":["15-25","6-15","6-12","10-20","20-25","12-22","20-20","10-15","8-15","10-15","6-12","8-20","10-10","5-8","4-10","4-12","10-15","8-12","2-6","5-12"]},{"type":"UM","states":["elliptic","lanceolate","oblanceolate","oblong","obovate","orbicular","ovate"],"id":8,"name":"leaf: blade: shape","data":[[1,2,4],[1,2,4,6,7],[4,5,7],[3,4,5],[2,4,5],[1,2,7],[1,4],[1,4,7],[1,4,7],[1,2],[2,4,7],[2,4],[3,4,5],[1,2,3],[1,2,4,7],[1,2],[1,4,7],1,[2,4,7],[1,7]]},{"type":"RN","unit":"mm","id":9,"name":"leaf: blade: length","data":["140-340","70-200","70-200","50-160","120-280","130-180","140-250","80-180","80-140","80-140","100-180","60-140","50-100","40-90","50-80","35-80","120-200","80-150","60-100","75-120"]},{"type":"RN","unit":"mm","id":10,"name":"leaf: blade: width","data":["40-120","30-70","30-60","20-50","70-120","40-80","50-100","40-80","25-65","20-40","30-50","20-50","20-35","20-35","15-35","8-25","40-70","30-60","15-35","40-63"]},{"type":"RN","id":11,"name":"leaf: blade: length: width ratio","data":["2.8-3.5","2.3-2.9","2.3-3.4","2.5-4.5","1.7-2.4","2.2-3.3","2.5-2.8","1.7-2","2.1-3.2","3.5-4","2.6-3.6","2.8-3","2.5-2.9","2-2.6","2.2-3.4","3.2-4.4","2.5-3","2.1-2.7","2.8-4","1.8-2"]},{"type":"UM","states":["leathery","membranous","papery"],"id":12,"name":"leaf: blade: texture","data":[1,1,1,3,3,3,1,1,[1,2],1,3,3,1,2,3,3,3,3,3,1]},{"type":"IN","min":3,"max":50,"id":13,"name":"leaf: blade: veins: number of pairs","data":[[34,35,32,33,38,39,36,37,40,25,27,26,29,28,31,30],[17,16,18,12,13,14,15],[10,11,12,13,14,15],[34,35,32,33,36,31,30],[9,10,11,12,13,14],[8,9,10,11,12],[34,35,32,33,38,39,36,37,42,43,40,41,46,47,44,45,50,49,48,31,30],[21,20,23,22,25,24,27,26,29,28,30],[5,6,7,8],[34,35,32,33,38,39,36,37,42,43,40,41,44,45,31,30],[12,13,14,15],[17,16,18,12,13,14,15],[17,16,18,10,11,12,13,14,15],[5,6,7,8],[3,4,5],[7,8,9,10,11,12,13],[8,9,10],[16,13,14,15],[21,20,23,22,25,24,27,26,29,28,30],0]},{"type":"UM","states":["attenuate","cuneate","decurrent","rounded"],"id":14,"name":"leaf: blade: base","data":[2,[2,4],2,[2,3],2,[2,3],[2,4],[2,4],[2,4],[2,3],2,[2,3],2,2,2,[1,3],[2,3],[2,3],[1,2],2]},{"type":"UM","states":["involute","recurved"],"id":15,"name":"leaf: blade: margin","data":[1,1,2,2,1,1,1,1,1,1,1,1,2,1,1,0,1,1,0,1]},{"type":"UM","states":["acuminate","acute","apiculate","caudate","emarginate","falcate","obtuse","rounded"],"id":16,"name":"leaf: blade: apex","data":[[1,2,7],[5,7,8],[1,2,7],[1,3,5,7,8],[1,7,8],[1,2],1,[1,7],[1,2],[1,2],1,[1,2,7],[2,7],[1,2],[1,4],[1,6,7],[1,2],[1,2],[1,4],[2,7,8]]},{"type":"UM","states":["dioecious","monoecious"],"id":17,"name":"plant: sexuality","data":[0,2,2,1,1,2,1,1,2,1,1,1,1,1,1,1,1,0,2,1]},{"type":"UM","states":["clustered flowers","corymbose cyme","cyme","cymule","pseudo-spike","solitary flowers","paired flowers","paniculiform cyme","paniculiform thyrse","thyrse","umbel"],"id":18,"name":"inflorescence: type","data":[2,[1,5,6],[6,10],[9,10],[6,7,8],8,[1,6,7],11,3,1,3,11,[3,6,11],[1,6],6,[6,7],[4,6],0,[6,7],6]},{"type":"IN","min":1,"max":14,"id":19,"name":"inflorescence: flowers: number","data":[[2,3,4,5,6,7,8,9,10,11,12,13,14],0,0,0,[1,2,8,9,10,11,12],0,[1,2,3,4,5,6,7,8,9],[2,3,4,5,6,7],[4,5,6,7,8,9,10],[1,2,3,4],[6,7,8,9,10],[1,3,4,5,6,7,8],0,[1,2,3,4,5],1,[1,2],[1,2,3],0,[1,2],1]},{"type":"RN","unit":"mm","id":20,"name":"inflorescence: length","data":[0,0,"50-70","80-100","80-150","40-80",0,0,0,0,0,0,0,0,0,0,0,0,0,0]},{"type":"RN","unit":"mm","id":21,"name":"inflorescence: peduncle: length","data":["6-12",0,0,0,"30-60",0,0,"10-30",0,0,"2-4",0,0,0,0,0,"0-10",0,0,0]},{"type":"RN","unit":"mm","id":22,"name":"pedicel: length","data":["18-30",0,"8-15","3-5","30-70","8-12","12-12","6-13","3-5","1-2","1-2","2-8","3-7","4-6",0,"2-2","2-5",0,"6-6","6-10"]},{"type":"UM","states":["2 large and 2 small","2 inner large and 3 outer small","3 large and 1 small","3 large and 2 small","4","5"],"id":23,"name":"sepals and petals: number","data":[[4,6],[2,6],[1,5],5,5,[1,5],5,5,5,5,5,5,5,5,[1,5],[1,5],[1,3,5],5,5,[1,5]]},{"type":"UM","states":["elliptic","obovate","orbicular","ovate","spatulate","triangular"],"id":24,"name":"sepal: shape","data":[0,3,0,0,[3,4],[3,4,6],0,0,3,0,0,0,3,1,[1,4],[1,3],2,0,0,[1,3,5]]},{"type":"UM","states":["orange","yellow"],"id":25,"name":"petal: color","data":[0,2,1,2,2,[1,2],0,0,0,0,2,2,[1,2],0,0,0,2,0,0,0]},{"type":"UM","states":["elliptic","lanceolate","oblong","obovate","orbicular","ovate"],"id":26,"name":"petal: shape","data":[0,4,4,0,[2,3],0,0,0,6,[4,6],4,0,[3,4],0,5,3,[1,3],0,0,4]},{"type":"IN","min":0,"max":5,"id":27,"name":"stamen or staminode fascicles: number","data":[5,5,0,4,0,0,4,0,0,4,4,4,0,0,0,0,0,0,4,4]},{"type":"IN","min":2,"max":40,"id":28,"name":"stamen or staminode fascicle: with stamens or staminodes: number","data":[[2,3,4,5],[6,7,8,9,10],0,0,0,0,0,0,0,0,0,0,0,40,12,4,0,0,0,0]},{"type":"UM","states":["cylindric","globose","oblong","ovoid","turbinate"],"id":29,"name":"ovary: shape","data":[2,2,0,5,2,0,0,1,2,0,0,4,4,0,[3,4],4,2,0,2,0]},{"type":"IN","min":1,"max":12,"id":30,"name":"ovary: locules: number","data":[5,[3,4,5],0,4,[8,9,10],[10,11,12],[5,6,7,8],1,1,0,1,[4,5,6,7,8],[8,9,10],0,4,0,[8,9,10,11,12],0,2,0]},{"type":"UM","states":["peltate","radiate"],"id":31,"name":"stigma: shape","data":[1,1,1,1,2,0,0,1,1,0,1,2,1,0,1,2,0,0,0,0]},{"type":"UM","states":["entire","3-cleft","4-cleft","4-lobed","5-cleft","5-lobed","6-lobed","7-lobed","8-lobed","9-lobed","10-lobed"],"id":32,"name":"stigma: division","data":[[2,3,5],5,4,4,[9,10,11],0,[6,7],0,1,0,4,[4,6,7,8,9],[9,10,11],0,0,0,1,0,0,0]},{"type":"UM","states":["brown","green","orange","purple","red","yellow","with yellow-brown spots"],"id":33,"name":"berry: color","data":[6,6,6,0,6,6,[4,5,7],0,0,0,6,[1,6],0,0,0,0,[2,3],0,0,0]},{"type":"UM","states":["ellipsoid","fusiform","globose","oblate","oblique","oblong","obovoid","ovoid"],"id":34,"name":"berry: shape","data":[[3,5,8],6,[7,8],1,4,3,3,[5,8],[1,8],0,[1,3,8],[3,5,8],[3,8],0,[1,2],3,[4,8],0,3,[1,3]]},{"type":"RN","unit":"mm","id":35,"name":"berry: length","data":[0,0,"30-50",0,"100-180",0,0,"22-40","32-35",0,"25-35","50-60","20-40",0,"15-18",0,"60-80",0,0,"20-30"]},{"type":"RN","unit":"mm","id":36,"name":"berry: diam.","data":["30-50",0,"25-30",0,"110-200","40-50","50-80","15-30","22-25",0,"15-25","40-50","20-35",0,"5-10","30-30","50-90","20-25","10-15","20-20"]},{"type":"IN","min":1,"max":10,"id":37,"name":"seeds: number","data":[[1,2,3,4],[1,2,3,4],[1,2],0,[8,9,10],[2,3,4],[4,5,6,7],1,2,0,[1,2],[2,3,4],1,0,2,0,[2,3,4],2,[1,2],0]},{"type":"UM","states":["fusiform","oblong","ovoid","reniform","rhomboid"],"id":38,"name":"seed: shape","data":[[2,3],0,2,0,4,3,0,0,0,0,0,1,0,0,0,0,[3,5],0,0,0]},{"type":"RN","unit":"mm","id":39,"name":"seed: length","data":[0,0,"20-25",0,0,"20-25",0,0,0,0,0,"25-25",0,0,0,0,"25-30",0,0,0]},{"type":"UM","states":["Jan","Feb","Mar","Apr","May","Jun","Jul","Aug","Sep","Oct","Nov","Dec"],"id":40,"name":"flowering","data":[[3,4,5],0,[6,7,8],[4,5],[8,9,10,11,12],[1,2],[9,10],[4,5],[6,7],[6,7],[1,2,12],5,[4,5],[1,12],[6,7],[4,5],[8,9,10],0,[4,5],0]},{"type":"UM","states":["Jan","Feb","Mar","Apr","May","Jun","Jul","Aug","Sep","Oct","Nov","Dec"],"id":41,"name":"fruiting","data":[[8,9,10,11],0,[11,12],[6,7,8],[1,12],[4,5],[11,12],[11,12],[11,12],0,[8,9],[7,8,9,10],[10,11,12],0,[10,11,12],[9,10],[6,7,8],5,[2,3,4],0]},{"type":"RN","unit":"m","id":42,"name":"distribution: elevation","data":["100-1400",0,"100-1900","1300-1600","200-1500","600-600",0,"400-1800","300-800","600-600","800-1700","100-1300","200-1200","300-400","200-1200","500-600","900-1700","800-1000","600-1800",0]},{"type":"UM","states":["Fujian","Guangdong","Guangxi","Guizhou","Hainan","Hunan","Jiangxi","Taiwan","Xizang","Yunnan"],"id":43,"name":"distribution: province","data":[[2,3,10],8,[1,2,3,4,5,6,7,8,10],10,[9,10],10,[1,2,5,8,10],[3,10],[3,10],3,[9,10],10,[2,3,5],10,[2,5],3,10,10,10,8]},{"type":"UM","states":["Bangladesh","Bhutan","Cambodia","India","Indonesia","Japan","Laos","Malaysia","Myanmar","Nepal","Philippines","Sri Lanka","Thailand","Vietnam"],"id":44,"name":"distribution: adjacent country","data":[[1,2,3,4,6,7,9,10,13,14],[5,6,11,12],14,0,[1,4],0,5,0,0,0,0,[1,3,4,7,8,14],0,0,14,0,0,0,0,0]}],"taxa":[{"id":1,"name":"Garcinia xanthochymus"},{"id":2,"name":"Garcinia subelliptica"},{"id":3,"name":"Garcinia multiflora"},{"id":4,"name":"Garcinia yunnanensis"},{"id":5,"name":"Garcinia pedunculata"},{"id":6,"name":"Garcinia xishuanbannaensis"},{"id":7,"name":"Garcinia mangostana"},{"id":8,"name":"Garcinia bracteata"},{"id":9,"name":"Garcinia paucinervis"},{"id":10,"name":"Garcinia kwangsiensis"},{"id":11,"name":"Garcinia nujiangensis"},{"id":12,"name":"Garcinia cowa"},{"id":13,"name":"Garcinia oblongifolia"},{"id":14,"name":"Garcinia erythrosepala"},{"id":15,"name":"Garcinia oligantha"},{"id":16,"name":"Garcinia subfalcata"},{"id":17,"name":"Garcinia esculenta"},{"id":18,"name":"Garcinia tetralata"},{"id":19,"name":"Garcinia lancilimba"},{"id":20,"name":"Garcinia linii"}],"dataDir":"flora_huh_harvard_edu_china_delta_Garcinia"}