{"id":2,"inkURL":"http://flora.huh.harvard.edu/china/delta/Rheum/Rheum.ink","title":"Rheum","imagePath":"http://flora.huh.harvard.edu/china/delta/Rheum/images","characters":[{"type":"RN","unit":"cm tall","id":1,"name":"plant: height","data":["50-150","70-200","50-150","80-150","50-100","50-100","60-80","40-90","30-70","100-100","100-100","150-200","150-200","60-200","100-100","50-80","50-80","30-60","25-55","50-70","30-55","20-35","10-25","15-28","15-20","15-30","20-35","15-25","35-50",0,0,0,0,0,0,"2-8","100-200","40-80"]},{"type":"UM","states":["absent","present"],"id":2,"name":"stem: presence","data":[2,2,2,2,2,2,2,2,2,2,2,2,2,2,2,2,2,2,2,2,2,2,2,2,2,2,2,2,2,1,1,1,1,1,1,1,2,2]},{"type":"UM","states":["hollow","not hollow"],"id":3,"name":"stem: hollow or not","data":[1,0,1,0,1,1,1,0,0,1,0,1,1,1,0,1,1,0,1,1,1,0,0,2,0,0,0,0,1,0,0,0,0,0,0,0,0,1]},{"type":"UM","states":["glabrous","hispid","hispidulous","muricate","papilliferous","pilose","pubescent"],"id":4,"name":"stem: indumentum","data":[[1,6],1,[1,5],[1,4],[1,5],1,[1,7],[1,2],[1,7],1,1,7,[1,4],[1,7],0,1,0,[5,7],[3,4],1,1,[4,7],6,6,7,0,0,0,1,0,0,0,0,0,0,0,1,1]},{"type":"RN","unit":"mm","id":5,"name":"petiole: length","data":[0,0,0,"170-250",0,0,0,"25-80","30-70",0,0,0,0,0,0,0,"140-180","50-80",0,"40-90","30-60","20-40",0,0,0,"30-50","20-45","30-105",0,"30-100","30-60","20-70","40-100","30-60","20-50",0,"50-150",0]},{"type":"UM","states":["green","purple","red"],"id":6,"name":"leaf blade: color abaxially","data":[[1,2,3],0,0,0,0,0,0,2,0,0,0,0,0,0,0,[2,3],0,0,1,0,[2,3],0,0,1,2,0,1,0,0,[2,3],2,0,[2,3],0,[2,3],[2,3],0,0]},{"type":"UM","states":["blue","green","yellow"],"id":7,"name":"leaf blade: color adaxially","data":[2,0,2,[1,2],0,0,0,0,0,0,0,0,0,0,0,2,0,0,2,0,0,2,0,2,2,0,[2,3],0,0,[2,3],2,0,[2,3],0,0,2,0,0]},{"type":"UM","states":["cordate","elliptic","lanceolate","oblong","orbicular","ovate","reniform","rhombic","triangular"],"id":8,"name":"leaf blade: shape","data":[[1,6,9],[2,6],[1,7],[1,6],[6,9],[1,6,9],6,[5,6],[6,9],[1,6],[1,6],[5,6],0,[5,6],6,1,[1,7],[1,7],[1,6,9],[1,6],[3,6],[6,9],[2,6],[2,4,5,6],[1,6,9],6,[5,7],1,[1,5],[2,6],[6,9],[2,8],[6,8],6,[6,9],[5,7],0,[2,6]]},{"type":"RN","unit":"mm","id":9,"name":"leaf blade: length","data":["120-570","200-500","200-250","250-400","150-260","150-300","120-200","80-160","80-200",0,"110-250",0,"400-600","300-600","250-360","130-200","180-280","50-70","60-110",0,"50-150","70-135","15-50","30-60","60-120","80-120","60-140","120-280","200-350","100-200","60-120","100-160","100-200","120-250","50-180","20-30",0,"90-140"]},{"type":"RN","unit":"mm","id":10,"name":"leaf blade: width","data":["100-610","180-400","250-300","230-280","100-200","130-220","100-180","80-140","60-130","200-300","100-170","300-500",0,0,"200-240","120-190",0,"60-85","40-85","100-200","30-55","50-95","10-30","25-50","40-70","40-75","80-160","130-270","270-500","80-150","40-85","84-140","90-170","100-220","50-90","30-40",0,"65-90"]},{"type":"UM","states":["glabrous","hispid","hispidulous","muricate","papilliferous","pilose","pubescent"],"id":11,"name":"leaf blade: abaxial indumentum","data":[7,6,0,1,7,[5,7],2,7,2,7,7,7,7,7,0,7,7,7,3,1,1,[1,3],6,3,3,1,1,7,[1,5],5,[1,5],5,[1,5],5,5,[1,4],0,1]},{"type":"UM","states":["glabrous","hispid","hispidulous","muricate","papilliferous","pilose","pubescent","tuberculate"],"id":12,"name":"leaf blade: adaxial indumentum","data":[[1,7],0,4,1,1,1,[1,7],[1,2],1,1,1,[1,7],0,[4,5],0,1,1,1,0,1,1,[1,3],[1,6],[1,3],1,1,8,1,0,[1,5],1,1,1,0,1,0,0,1]},{"type":"IN","min":3,"max":11,"id":13,"name":"leaf blade: veins: number","data":[[5,6,7],[5,6,7],5,5,[5,6,7],0,[5,6,7,8,9],[5,6,7],5,[5,6,7],0,[5,6,7],5,5,0,5,5,5,5,[3,4,5,6,7],[3,4,5],5,[3,4,5],[3,4,5],[3,4,5],[8,9,10,11],[3,4,5],5,0,5,5,5,[5,6,7],[5,6,7],5,[5,6,7],0,[5,6,7]]},{"type":"UM","states":["cordate","cuneate","rounded","truncate"],"id":14,"name":"leaf blade: base","data":[1,1,1,1,1,1,1,1,1,1,0,1,1,1,0,1,1,1,1,1,3,[1,4],1,1,1,[2,3],[1,3],[1,3],1,[1,3],[1,3],2,1,[1,3],[1,3],1,0,0]},{"type":"UM","states":["crispate","entire","palmately divided","palmatilobate","pinnate","pinnatisect","serrulate","sinuate","sinuolate"],"id":15,"name":"leaf blade: margin","data":[[1,8],[2,9],9,9,9,9,2,2,9,2,2,4,6,3,3,2,2,2,2,9,[2,9],9,2,[2,9],2,9,2,2,7,[2,9],[2,3,5],2,[2,9],[2,9],9,2,0,0]},{"type":"UM","states":["acuminate","acute","obtuse","retuse","rounded"],"id":16,"name":"leaf blade: apex","data":[[2,3],3,3,[2,3],[2,3],3,3,[2,3],[2,3],3,1,2,[1,2],2,2,[1,3],1,1,1,3,2,3,3,3,1,[2,3],5,3,3,3,[2,3],[2,3],3,3,2,[3,4],0,0]},{"type":"UM","states":["cordate","lanceolate","linear","orbicular","ovate","reniform","triangular"],"id":17,"name":"stem leaf: shape","data":[[5,7],5,5,[5,7],0,0,5,5,0,0,0,0,0,0,0,[1,5],6,1,0,0,[2,5,7],0,2,3,0,0,0,0,4,0,0,0,0,0,0,0,[1,4,5],5]},{"type":"RN","unit":"mm","id":18,"name":"ocrea: length","data":[0,0,0,"50-80","40-80","30-60",0,0,0,0,0,"75-150","75-150",0,"70-70","20-20","15-25","15-25","15-20","7-15","10-10",0,"5-5",0,"30-40",0,0,0,0,0,0,0,0,0,0,0,"100-150","70-70"]},{"type":"UM","states":["headlike","panicle","spiciform"],"id":19,"name":"inflorescence: type","data":[2,2,2,2,2,2,2,2,2,2,2,2,2,2,2,2,2,2,2,2,2,2,2,2,2,2,2,2,2,[2,3],[2,3],[2,3],[2,3],[2,3],[2,3],[1,2],2,2]},{"type":"IN","min":1,"max":10,"id":20,"name":"flowers: number per fascicle","data":[[3,4,5,6,7,8],0,0,0,0,0,0,0,0,0,0,0,0,0,0,10,0,[1,2,3,4],[2,3,4,5],0,[4,5],0,[2,3],[3,4],[3,4,5],[2,3,4],0,0,[1,2],0,0,0,0,0,0,0,[5,6,7,8,9],0]},{"type":"RN","unit":"mm","id":21,"name":"pedicel: length","data":[0,0,0,"4-5","3-3",0,"2-3","2.5-3","2.5-3",0,0,"3-3.5","2-2.5","2-3","1.5-2","3-3","2-2","4-7","2-3",0,"2.5-3","2.5-3.5","2-3","3-4.5","2-2","3-3","1.5-3","2-3.5","2.5-5","3-3","2-2",0,"2-2","3-3","1.5-2",0,"2-3","2.5-4"]},{"type":"IN","min":4,"max":6,"id":22,"name":"tepals: number","data":[6,0,0,6,0,0,0,0,0,0,0,6,6,0,0,6,6,6,6,6,6,6,0,0,6,0,6,0,0,0,0,0,0,0,0,6,[4,5,6],[4,5,6]]},{"type":"UM","states":["green","purple","red","white","yellow"],"id":23,"name":"tepal: color","data":[[1,4,5],[2,3],[4,5],0,[1,4],[4,5],[1,5],[1,4],[1,2],5,0,[1,4,5],[2,3,4,5],[2,3],[1,4,5],[2,3],3,2,[1,2,4],0,0,[4,5],0,0,[2,3],[2,3],[4,5],[1,2,3,5],[4,5],1,[3,4,5],[2,3],[4,5],[4,5],[4,5],[1,4],[1,5],1]},{"type":"UM","states":["broad","elliptic","lanceolate","oblong","obovate","orbicular","ovate"],"id":24,"name":"tepal: shape","data":[[1,6],[2,4,6],2,2,[2,5],[2,4],3,[2,6],7,2,7,2,[2,6],6,[2,5],[2,6,7],6,[2,7],2,2,2,2,2,2,[2,7],2,[2,3,7],2,2,[2,4],[2,4],[2,4],7,2,2,[4,5],0,0]},{"type":"RN","unit":"mm","id":25,"name":"outer tepal: length","data":[0,"1.5-1.5",0,"2-2.5",0,0,"1.8-1.8",0,0,"2-2","1.5-2","2-2.5","1-1.5",0,0,"1.8-1.8","1-1.5","3-3.5",0,0,"1.5-1.5","2-2","1.5-2","1.5-2","1.5-1.5","1-1.5","2-2.5","2.5-2.5",0,"1.8-2",0,"1.5-2","1.2-1.2","1.8-2","1-1","3-3.5",0,"1.5-1.5"]},{"type":"RN","unit":"mm","id":26,"name":"inner tepal: length","data":["2-2","2.5-2.5",0,"2-2.5","1.5-1.5","1.5-1.5",0,"2-2.2",0,"2-2","1.5-2","2-2.5",0,"1.5-1.5","2.5-2.5","2-2.5","1-1.5",0,"1.5-1.5","1.5-2",0,0,"1.5-2","2.5-2.5",0,0,"3.5-3.5","2.5-2.5","2-2",0,"2-2","1.5-2",0,0,0,0,"2-2","1.5-1.5"]},{"type":"RN","unit":"mm","id":27,"name":"filament: length","data":[0,0,0,0,0,0,"1-1",0,0,0,0,0,0,0,0,"2-2",0,"1.5-2",0,0,0,0,0,"1-1.5",0,"0.5-1",0,0,"1-1",0,0,0,0,"1.5-1.5",0,0,0,"2.5-3"]},{"type":"UM","states":["black","brown","purple","red","yellow"],"id":28,"name":"anther: color","data":[0,0,0,0,0,0,[3,4],0,0,0,3,0,0,0,0,[1,3],3,[3,4],[3,4],0,0,0,0,3,0,0,0,[2,5],0,5,[3,4],0,0,0,0,0,0,0]},{"type":"UM","states":["elliptic","globose","oblong","ovoid"],"id":29,"name":"anther: shape","data":[0,0,0,0,0,0,1,0,0,0,[2,4],0,0,0,0,0,2,2,0,3,0,0,0,[1,2],1,0,0,0,3,0,0,0,0,1,0,[1,3],[1,3],[1,3]]},{"type":"UM","states":["circular","ellipsoid","oblong","obovoid","ovoid","rhomboid","triangular"],"id":30,"name":"ovary: shape","data":[[2,3],[4,6],0,2,0,0,4,[1,6],0,0,0,0,[5,6],5,5,[2,6],2,2,[2,4,6],0,[2,4],5,2,0,2,[5,6],[2,6],0,[5,7],4,0,0,2,0,[2,4],6,5,[4,6]]},{"type":"UM","states":["compressed","discoid","inflated","oblate"],"id":31,"name":"stigma: shape","data":[0,4,0,3,0,0,3,0,0,0,0,3,3,3,3,0,3,0,3,0,3,0,3,1,3,3,3,0,2,0,0,0,3,0,3,3,3,3]},{"type":"UM","states":["cordate","cuneate","ellipsoid","oblong","orbicular","ovoid","reniform","rhomboid","spherical","triangular"],"id":32,"name":"fruit: shape","data":[[3,6,10],[3,6],[3,5],5,[4,5],[3,4],[3,5],6,9,3,[4,6],[3,4],[3,4],[4,6],0,[4,6],0,[3,6],6,[3,4,6],[3,6],5,[6,10],[1,5],1,[3,4],7,6,[3,6,10],[3,4],6,2,6,[3,6],6,6,6,[3,8]]},{"type":"RN","unit":"mm","id":33,"name":"fruit: length","data":[0,"90-100","10-12","7.5-8.5","12-12","5.5-7.5","9-10","8.5-9",0,"12-12","5-8","8-10","8-9","8-9.5",0,"7-8",0,"13-13","6.5-8","12-12","8.5-8.5","9-10","5-6",0,"7.5-8.5","14-16","10-12","10-10","10-12","8-10","7-8","5.5-12.5","8.5-10","10-11","7.5-8.5",0,"6-7","7-8"]},{"type":"RN","unit":"mm","id":34,"name":"fruit: diam.","data":[0,"70-85",0,0,"15-15","4.5-6","8-9.5","7-7.5","8-9","11-11",0,"7-9","7-7.5","7-7.5",0,"6.5-7",0,"10-10",0,"8.5-9.5","6-6.5","8-9.5",0,"8-9","8.5-9.5","13-15","12-14","8-9","6-9","7-9","5-6","5.5-15","7-8.5","7-8","7-8",0,"5-6","5-6"]},{"type":"RN","unit":"mm","id":35,"name":"fruit: wing: length","data":["1.5-2",0,"3.5-3.5",0,"4-5",0,0,0,0,0,"2.5-3.5",0,0,0,0,0,0,0,0,0,0,0,0,0,"2.5-3",0,0,0,0,0,"1-1.5",0,0,0,0,0,"0.5-1","0.5-0.5"]},{"type":"RN","unit":"mm","id":36,"name":"fruit: wing: width","data":[0,"2.5-2.5",0,"2-2.5",0,"1-1.5","1.5-1.5","2-2","1.5-2","3-3",0,"3-3","2.5-2.5","2-2.5",0,0,0,0,"1.5-1.5",0,"1.5-1.5",0,"1-1.5","2.5-2.5",0,"5-5",0,0,"1.5-1.5","2.5-3.5",0,"3-5","3-3","2-2","2.5-2.5",0,0,0]},{"type":"UM","states":["black","brown","red","yellow","with black stripes","with black-brown stripe"],"id":37,"name":"seed: color","data":[2,0,0,0,0,[1,2],[2,4],0,0,2,0,0,[1,2],1,0,2,0,0,[2,4,5],2,2,0,0,0,[2,3,6],2,0,[1,2],2,0,0,0,2,0,0,0,[1,2],0]},{"type":"UM","states":["cordate","ellipsoid","orbicular","ovoid","triangular"],"id":38,"name":"seed: shape","data":[[2,4],4,[2,4],4,4,4,[2,4],4,[3,4],4,4,4,4,4,0,4,0,0,4,[2,4],4,4,4,4,[4,5],4,4,4,4,0,4,4,4,4,4,0,[1,4],0]},{"type":"RN","unit":"mm","id":39,"name":"seed: width","data":[0,0,"4-4",0,"6-6",0,"6-7","3-3","5-5",0,0,0,0,0,0,0,0,0,"3-3",0,0,0,"2-2.5",0,0,"3-3","5-5",0,"5-5",0,"3-3","3-5","3-3",0,0,0,0,0]},{"type":"UM","states":["May","Jun","Jul","Aug"],"id":40,"name":"flowering","data":[2,[2,3],0,[1,2,3],[2,3],[2,3],[2,3],3,[3,4],[2,3],[2,3],[1,2],2,2,0,[2,3],2,[3,4],[2,3],[2,3],2,3,[2,3],[2,3],3,[1,2,3],[1,2],3,1,2,3,[2,3],3,2,2,[2,3],[2,3],[2,3]]},{"type":"UM","states":["Jun","Jul","Aug","Sep","Oct"],"id":41,"name":"fruiting","data":[[3,4],[3,4],[3,4],[2,3,4],[3,4],[2,3],[3,4],[3,4],[4,5],3,[3,4],[3,4],3,[2,3],0,[3,4],0,[4,5],[2,3],[2,3],3,[3,4],[3,4],[3,4],[3,4],[3,4],[2,3,4],3,[1,2],3,[3,4],[3,4],3,[3,4],[2,3],[3,4,5],4,4]},{"type":"RN","unit":"m","id":42,"name":"distribution: elevation","data":["1000-1600","3400-4300","3500-3600","1000-1800","1200-2600","1900-2400","3000-3000","2500-4000","4200-4600","2000-2000","3000-3500","1200-4000","1500-4400","1600-3000","3000-3000","2800-4000",0,"4000-4000","2800-3900","1300-2000","2400-3000","4000-4200","2800-4500","3000-4800","3500-4300","1100-2300","700-2000","4000-4600","500-1000","4000-5000","4500-5300","4700-5400","1500-5000","2600-4200","2900-4200","4500-5000","4000-4800","3000-4600"]},{"type":"UM","states":["Fujian","Gansu","Guizhou","Hebei","Heilongjiang","Henan","Hubei","Jilin","Nei Mongol","Ningxia","Qinghai","Shaanxi","Shanxi","Sichuan","Xinjiang","Xizang","Yunnan"],"id":43,"name":"distribution: province","data":[[4,5,7,8,9,13],16,16,[2,12,13],15,15,[17,16,14],[17,16,14],16,15,2,[17,1,3,6,7,12,14],[17,16,2,7,9,11,12,14],[16,2,11,12],14,[17,16,2,14],14,17,[17,2,14],[2,9,10],[2,11,15],16,[16,2,11,14],[17,14],14,[2,9,11],[2,9,15],16,15,16,16,16,[2,11,14],15,[11,15],16,16,[17,16,14]]},{"type":"UM","states":["Afghanistan","Bhutan","India","Kashmir","Kazakhstan","Kyrgyzstan","Mongolia","Myanmar","Nepal","Pakistan","Russia","Tajikistan"],"id":44,"name":"distribution: adjacent country","data":[[7,11],[3,8,9,10],[3,4,9,10],0,[5,6],[5,7,11],0,0,0,[5,7,11],0,0,11,0,0,[2,3,4,8,9],0,8,0,7,0,0,0,[2,9],0,7,[5,7,11],[1,4,10],[1,5,11],[1,2,3,4,10],[1,3,9,10,12],0,0,5,[5,6,12],3,[1,2,3,8,9,10],0]}],"taxa":[{"id":1,"name":"Rheum rhabarbum"},{"id":2,"name":"Rheum australe"},{"id":3,"name":"Rheum webbianum"},{"id":4,"name":"Rheum hotaoense"},{"id":5,"name":"Rheum wittrockii"},{"id":6,"name":"Rheum altaicum"},{"id":7,"name":"Rheum forrestii"},{"id":8,"name":"Rheum likiangense"},{"id":9,"name":"Rheum lhasaense"},{"id":10,"name":"Rheum compactum"},{"id":11,"name":"Rheum glabricaule"},{"id":12,"name":"Rheum officinale"},{"id":13,"name":"Rheum palmatum","images":[{"f":"palmatum5.jpg","n":""},{"f":"palmatum4.jpg","n":""},{"f":"palmatum3.jpg","n":""},{"f":"palmatum2.jpg","n":""},{"f":"palmatum.jpg","n":""}]},{"id":14,"name":"Rheum tanguticum"},{"id":15,"name":"Rheum laciniatum"},{"id":16,"name":"Rheum acuminatum"},{"id":17,"name":"Rheum maculatum"},{"id":18,"name":"Rheum yunnanense"},{"id":19,"name":"Rheum kialense"},{"id":20,"name":"Rheum racemiferum"},{"id":21,"name":"Rheum sublanceolatum"},{"id":22,"name":"Rheum inopinatum"},{"id":23,"name":"Rheum pumilum"},{"id":24,"name":"Rheum delavayi","images":[{"f":"delavayi3.jpg","n":""},{"f":"delavayi2.jpg","n":""},{"f":"delavayi.jpg","n":""}]},{"id":25,"name":"Rheum subacaule"},{"id":26,"name":"Rheum uninerve"},{"id":27,"name":"Rheum nanum"},{"id":28,"name":"Rheum tibeticum"},{"id":29,"name":"Rheum tataricum"},{"id":30,"name":"Rheum spiciforme"},{"id":31,"name":"Rheum moorcroftianum"},{"id":32,"name":"Rheum rhomboideum"},{"id":33,"name":"Rheum przewalskyi","images":[{"f":"przewalskii3.jpg","n":""},{"f":"przewalskii2.jpg","n":""},{"f":"przewalskii.jpg","n":""}]},{"id":34,"name":"Rheum rhizostachyum"},{"id":35,"name":"Rheum reticulatum"},{"id":36,"name":"Rheum globulosum"},{"id":37,"name":"Rheum nobile"},{"id":38,"name":"Rheum alexandrae","images":[{"f":"alexandrae5.jpg","n":""},{"f":"alexandrae4.jpg","n":""},{"f":"alexandrae3.jpg","n":""},{"f":"alexandrae2.jpg","n":""},{"f":"alexandrae.jpg","n":""}]}],"dataDir":"flora_huh_harvard_edu_china_delta_Rheum_Rheum"}