{"id":278,"inkURL":"http://sharkeylab.org/sharkeylab/Misc/datasets/mendesellinae.ink","title":"MENDESELLINAE GENERA OF THE NEW WORLD","imagePath":"http://www.sharkeylab.org/sharkeylab/Misc/datasets/mendesellinae","characters":[{"type":"UM","states":["at least partially infuscate","wings clear"],"id":1,"name":"wings \u003cinfuscate\u003e","images":[{"f":"mendes02.gif","n":""}],"data":[1,2]},{"type":"UM","states":["acute apically","truncate apically"],"id":2,"name":"hypopygium \u003cshape apically\u003e","images":[{"f":"mend0102.gif","n":""}],"data":[1,2]}],"taxa":[{"id":1,"name":"Mendesella","images":[{"f":"MendesellaWing.gif","n":""}]},{"id":2,"name":"Epsilogaster","images":[{"f":"EpsilogasterWing.gif","n":""}]}],"dataDir":"sharkeylab_org_sharkeylab_Misc_datasets_mendesellinae"}